midi_to_noteblock/__init__.py
midi_to_noteblock/audio_splitter.py
midi_to_noteblock/block.py
midi_to_noteblock/nbt_gen.py
midi_to_noteblock/region.py
midi_to_noteblock-0.0.3.data/scripts/main.py
midi_to_noteblock-0.0.3.dist-info/LICENSE
midi_to_noteblock-0.0.3.dist-info/METADATA
midi_to_noteblock-0.0.3.dist-info/WHEEL
midi_to_noteblock-0.0.3.dist-info/entry_points.txt
midi_to_noteblock-0.0.3.dist-info/top_level.txt
midi_to_noteblock-0.0.3.dist-info/RECORD
