Metadata-Version: 2.1
Name: midi-to-noteblock
Version: 0.0.3
Summary: A CLI to convert midi files into world edit schematic files.
Home-page: https://github.com/SushiWaUmai/midi-to-noteblock
Author: Eugene Matsumura
License: MIT
Platform: any
Requires-Python: >=3.8
Requires-Dist: NBT
Requires-Dist: pretty-midi
